{
  "uuid": "b3ac986f-e79e-41ef-926d-31a86c3c75ed",
  "starterPrompted": true,
  "starterLocked": false,
  "starterSelected": true,
  "starterUUID": "1a1e8374-b3ca-4261-bd92-417753e1d49f",
  "keyItems": [],
  "battleTheme": "cobblemon:battle.pvp.default",
  "extraData": {
    "cobbledex_discovery": {
      "registers": {
        "mudkip": {
          "normal": {
            "isShiny": false,
            "status": "CAUGHT",
            "discoveredTimestamp": 1735139519117,
            "caughtTimestamp": 1735139519117
          }
        },
        "drowzee": {
          "normal": {
            "isShiny": false,
            "status": "SEEN",
            "discoveredTimestamp": 1735140029074
          }
        },
        "bunnelby": {
          "normal": {
            "isShiny": false,
            "status": "CAUGHT",
            "discoveredTimestamp": 1735140033624,
            "caughtTimestamp": 1735150311011
          }
        },
        "tandemaus": {
          "normal": {
            "isShiny": false,
            "status": "CAUGHT",
            "discoveredTimestamp": 1735140046175,
            "caughtTimestamp": 1735225738779
          }
        },
        "voltorb": {
          "hisui": {
            "isShiny": false,
            "status": "SEEN",
            "discoveredTimestamp": 1735140089776
          },
          "normal": {
            "isShiny": false,
            "status": "SEEN",
            "discoveredTimestamp": 1735140790410
          }
        },
        "pidgey": {
          "normal": {
            "isShiny": false,
            "status": "SEEN",
            "discoveredTimestamp": 1735140233484
          }
        },
        "patrat": {
          "normal": {
            "isShiny": false,
            "status": "SEEN",
            "discoveredTimestamp": 1735140249385
          }
        },
        "wooloo": {
          "normal": {
            "isShiny": false,
            "status": "SEEN",
            "discoveredTimestamp": 1735140257268
          }
        },
        "bouffalant": {
          "normal": {
            "isShiny": false,
            "status": "SEEN",
            "discoveredTimestamp": 1735140264969
          }
        },
        "growlithe": {
          "normal": {
            "isShiny": false,
            "status": "CAUGHT",
            "discoveredTimestamp": 1735140320371,
            "caughtTimestamp": 1735141597422
          }
        },
        "mareep": {
          "normal": {
            "isShiny": false,
            "status": "SEEN",
            "discoveredTimestamp": 1735140327873
          }
        },
        "bidoof": {
          "normal": {
            "isShiny": false,
            "status": "SEEN",
            "discoveredTimestamp": 1735140341672
          }
        },
        "minun": {
          "normal": {
            "isShiny": false,
            "status": "SEEN",
            "discoveredTimestamp": 1735140344372
          }
        },
        "tauros": {
          "normal": {
            "isShiny": false,
            "status": "SEEN",
            "discoveredTimestamp": 1735140718324
          }
        },
        "zigzagoon": {
          "normal": {
            "isShiny": false,
            "status": "SEEN",
            "discoveredTimestamp": 1735140732874
          },
          "galar": {
            "isShiny": false,
            "status": "SEEN",
            "discoveredTimestamp": 1735144190373
          }
        },
        "koffing": {
          "normal": {
            "isShiny": false,
            "status": "SEEN",
            "discoveredTimestamp": 1735140762808
          }
        },
        "linoone": {
          "normal": {
            "isShiny": false,
            "status": "SEEN",
            "discoveredTimestamp": 1735140857513
          }
        },
        "lechonk": {
          "normal": {
            "isShiny": false,
            "status": "SEEN",
            "discoveredTimestamp": 1735140885214
          }
        },
        "yungoos": {
          "normal": {
            "isShiny": false,
            "status": "SEEN",
            "discoveredTimestamp": 1735140898417
          }
        },
        "taillow": {
          "normal": {
            "isShiny": false,
            "status": "SEEN",
            "discoveredTimestamp": 1735140957967
          }
        },
        "snubbull": {
          "normal": {
            "isShiny": false,
            "status": "SEEN",
            "discoveredTimestamp": 1735140970222
          }
        },
        "maschiff": {
          "normal": {
            "isShiny": false,
            "status": "SEEN",
            "discoveredTimestamp": 1735140975522
          }
        },
        "furret": {
          "normal": {
            "isShiny": false,
            "status": "SEEN",
            "discoveredTimestamp": 1735140984820
          }
        },
        "psyduck": {
          "normal": {
            "isShiny": false,
            "status": "SEEN",
            "discoveredTimestamp": 1735141083706
          }
        },
        "pidove": {
          "normal": {
            "isShiny": false,
            "status": "SEEN",
            "discoveredTimestamp": 1735141151159
          }
        },
        "combee": {
          "normal": {
            "isShiny": false,
            "status": "CAUGHT",
            "discoveredTimestamp": 1735141164810,
            "caughtTimestamp": 1735146419356
          }
        },
        "sentret": {
          "normal": {
            "isShiny": false,
            "status": "SEEN",
            "discoveredTimestamp": 1735141213162
          }
        },
        "metapod": {
          "normal": {
            "isShiny": false,
            "status": "SEEN",
            "discoveredTimestamp": 1735141253265
          }
        },
        "seedot": {
          "normal": {
            "isShiny": false,
            "status": "SEEN",
            "discoveredTimestamp": 1735141356607
          }
        },
        "kakuna": {
          "normal": {
            "isShiny": false,
            "status": "SEEN",
            "discoveredTimestamp": 1735141368509
          }
        },
        "stonjourner": {
          "normal": {
            "isShiny": false,
            "status": "SEEN",
            "discoveredTimestamp": 1735141479458
          }
        },
        "weezing": {
          "normal": {
            "isShiny": false,
            "status": "SEEN",
            "discoveredTimestamp": 1735141489559
          }
        },
        "illumise": {
          "normal": {
            "isShiny": false,
            "status": "SEEN",
            "discoveredTimestamp": 1735141604388
          }
        },
        "lillipup": {
          "normal": {
            "isShiny": false,
            "status": "SEEN",
            "discoveredTimestamp": 1735141630570
          }
        },
        "miltank": {
          "normal": {
            "isShiny": false,
            "status": "CAUGHT",
            "discoveredTimestamp": 1735141632209,
            "caughtTimestamp": 1735228970741
          }
        },
        "flabebe": {
          "normal": {
            "isShiny": false,
            "status": "SEEN",
            "discoveredTimestamp": 1735141659760
          }
        },
        "vivillon": {
          "normal": {
            "isShiny": false,
            "status": "SEEN",
            "discoveredTimestamp": 1735141687255
          }
        },
        "cutiefly": {
          "normal": {
            "isShiny": false,
            "status": "SEEN",
            "discoveredTimestamp": 1735141732670
          }
        },
        "diggersby": {
          "normal": {
            "isShiny": false,
            "status": "SEEN",
            "discoveredTimestamp": 1735141743508
          }
        },
        "lopunny": {
          "normal": {
            "isShiny": false,
            "status": "SEEN",
            "discoveredTimestamp": 1735141770859
          }
        },
        "mimejr": {
          "normal": {
            "isShiny": false,
            "status": "SEEN",
            "discoveredTimestamp": 1735141839963
          }
        },
        "elekid": {
          "normal": {
            "isShiny": false,
            "status": "CAUGHT",
            "discoveredTimestamp": 1735141916467,
            "caughtTimestamp": 1735142023668
          }
        },
        "meowth": {
          "normal": {
            "isShiny": false,
            "status": "SEEN",
            "discoveredTimestamp": 1735142110503
          },
          "galar": {
            "isShiny": false,
            "status": "SEEN",
            "discoveredTimestamp": 1735148252061
          }
        },
        "slowpoke": {
          "normal": {
            "isShiny": false,
            "status": "CAUGHT",
            "discoveredTimestamp": 1735142297183,
            "caughtTimestamp": 1735149859274
          }
        },
        "arcanine": {
          "normal": {
            "isShiny": false,
            "status": "SEEN",
            "discoveredTimestamp": 1735142363585
          }
        },
        "joltik": {
          "normal": {
            "isShiny": false,
            "status": "SEEN",
            "discoveredTimestamp": 1735142420861
          }
        },
        "grimer": {
          "normal": {
            "isShiny": false,
            "status": "SEEN",
            "discoveredTimestamp": 1735142583833
          }
        },
        "fletchling": {
          "normal": {
            "isShiny": false,
            "status": "CAUGHT",
            "discoveredTimestamp": 1735142670562,
            "caughtTimestamp": 1735145312412
          }
        },
        "natu": {
          "normal": {
            "isShiny": false,
            "status": "SEEN",
            "discoveredTimestamp": 1735142751903
          }
        },
        "honedge": {
          "normal": {
            "isShiny": false,
            "status": "CAUGHT",
            "discoveredTimestamp": 1735142774864,
            "caughtTimestamp": 1735145541860
          }
        },
        "deerling": {
          "normal": {
            "isShiny": false,
            "status": "SEEN",
            "discoveredTimestamp": 1735143127279
          }
        },
        "ponyta": {
          "normal": {
            "isShiny": false,
            "status": "SEEN",
            "discoveredTimestamp": 1735143135880
          }
        },
        "cottonee": {
          "normal": {
            "isShiny": false,
            "status": "CAUGHT",
            "discoveredTimestamp": 1735143144679,
            "caughtTimestamp": 1735220261105
          }
        },
        "krabby": {
          "normal": {
            "isShiny": false,
            "status": "CAUGHT",
            "discoveredTimestamp": 1735143154280,
            "caughtTimestamp": 1735149970257
          }
        },
        "wingull": {
          "normal": {
            "isShiny": false,
            "status": "SEEN",
            "discoveredTimestamp": 1735143163879
          }
        },
        "exeggcute": {
          "alolabias": {
            "isShiny": false,
            "status": "SEEN",
            "discoveredTimestamp": 1735143177731
          }
        },
        "timburr": {
          "normal": {
            "isShiny": false,
            "status": "SEEN",
            "discoveredTimestamp": 1735143300137
          }
        },
        "buneary": {
          "normal": {
            "isShiny": false,
            "status": "SEEN",
            "discoveredTimestamp": 1735143377983
          }
        },
        "shroomish": {
          "normal": {
            "isShiny": false,
            "status": "CAUGHT",
            "discoveredTimestamp": 1735143381625,
            "caughtTimestamp": 1735228318703
          }
        },
        "magikarp": {
          "normal": {
            "isShiny": false,
            "status": "SEEN",
            "discoveredTimestamp": 1735143474430
          }
        },
        "tinkatink": {
          "normal": {
            "isShiny": false,
            "status": "CAUGHT",
            "discoveredTimestamp": 1735143574685,
            "caughtTimestamp": 1735226428198
          }
        },
        "vulpix": {
          "normal": {
            "isShiny": false,
            "status": "SEEN",
            "discoveredTimestamp": 1735143584837
          },
          "alola": {
            "isShiny": false,
            "status": "CAUGHT",
            "discoveredTimestamp": 1735147137884,
            "caughtTimestamp": 1735147179313
          }
        },
        "ninetales": {
          "normal": {
            "isShiny": false,
            "status": "SEEN",
            "discoveredTimestamp": 1735143702426
          }
        },
        "teddiursa": {
          "normal": {
            "isShiny": false,
            "status": "SEEN",
            "discoveredTimestamp": 1735143839531
          }
        },
        "watchog": {
          "normal": {
            "isShiny": false,
            "status": "SEEN",
            "discoveredTimestamp": 1735143843232
          }
        },
        "starly": {
          "normal": {
            "isShiny": false,
            "status": "CAUGHT",
            "discoveredTimestamp": 1735143849681,
            "caughtTimestamp": 1735143894265
          }
        },
        "staravia": {
          "normal": {
            "isShiny": false,
            "status": "CAUGHT",
            "discoveredTimestamp": 1735143906588,
            "caughtTimestamp": 1735143906588
          }
        },
        "rookidee": {
          "normal": {
            "isShiny": false,
            "status": "SEEN",
            "discoveredTimestamp": 1735143915569
          }
        },
        "stantler": {
          "normal": {
            "isShiny": false,
            "status": "SEEN",
            "discoveredTimestamp": 1735143917318
          }
        },
        "swellow": {
          "normal": {
            "isShiny": false,
            "status": "CAUGHT",
            "discoveredTimestamp": 1735143953528,
            "caughtTimestamp": 1735226126552
          }
        },
        "lilligant": {
          "normal": {
            "isShiny": false,
            "status": "SEEN",
            "discoveredTimestamp": 1735143970222
          }
        },
        "bonsly": {
          "normal": {
            "isShiny": false,
            "status": "SEEN",
            "discoveredTimestamp": 1735144053625
          }
        },
        "sneasel": {
          "hisui": {
            "isShiny": false,
            "status": "SEEN",
            "discoveredTimestamp": 1735144116118
          }
        },
        "frillish": {
          "normal": {
            "isShiny": false,
            "status": "SEEN",
            "discoveredTimestamp": 1735144150368
          }
        },
        "tranquill": {
          "normal": {
            "isShiny": false,
            "status": "SEEN",
            "discoveredTimestamp": 1735144259769
          }
        },
        "mudbray": {
          "normal": {
            "isShiny": false,
            "status": "CAUGHT",
            "discoveredTimestamp": 1735144932115,
            "caughtTimestamp": 1735222861502
          }
        },
        "persian": {
          "normal": {
            "isShiny": false,
            "status": "SEEN",
            "discoveredTimestamp": 1735145134359
          },
          "alola": {
            "isShiny": false,
            "status": "CAUGHT",
            "discoveredTimestamp": 1735230023908,
            "caughtTimestamp": 1735230055637
          }
        },
        "flaaffy": {
          "normal": {
            "isShiny": false,
            "status": "SEEN",
            "discoveredTimestamp": 1735145177613
          }
        },
        "fletchinder": {
          "normal": {
            "isShiny": false,
            "status": "CAUGHT",
            "discoveredTimestamp": 1735145319208,
            "caughtTimestamp": 1735145319208
          }
        },
        "sawsbuck": {
          "normal": {
            "isShiny": false,
            "status": "SEEN",
            "discoveredTimestamp": 1735145361114
          }
        },
        "florges": {
          "normal": {
            "isShiny": false,
            "status": "SEEN",
            "discoveredTimestamp": 1735145484416
          }
        },
        "diglett": {
          "alola": {
            "isShiny": false,
            "status": "SEEN",
            "discoveredTimestamp": 1735146009084
          }
        },
        "dubwool": {
          "normal": {
            "isShiny": false,
            "status": "SEEN",
            "discoveredTimestamp": 1735146300431
          }
        },
        "pidgeotto": {
          "normal": {
            "isShiny": false,
            "status": "SEEN",
            "discoveredTimestamp": 1735146431484
          }
        },
        "beedrill": {
          "normal": {
            "isShiny": false,
            "status": "SEEN",
            "discoveredTimestamp": 1735146556079
          }
        },
        "pineco": {
          "normal": {
            "isShiny": false,
            "status": "CAUGHT",
            "discoveredTimestamp": 1735146743445,
            "caughtTimestamp": 1735146782231
          }
        },
        "lickitung": {
          "normal": {
            "isShiny": false,
            "status": "SEEN",
            "discoveredTimestamp": 1735146873490
          }
        },
        "crabrawler": {
          "normal": {
            "isShiny": false,
            "status": "SEEN",
            "discoveredTimestamp": 1735146897908
          }
        },
        "beartic": {
          "normal": {
            "isShiny": false,
            "status": "SEEN",
            "discoveredTimestamp": 1735146910974
          }
        },
        "staryu": {
          "normal": {
            "isShiny": false,
            "status": "SEEN",
            "discoveredTimestamp": 1735146975321
          }
        },
        "cubchoo": {
          "normal": {
            "isShiny": false,
            "status": "SEEN",
            "discoveredTimestamp": 1735147007212
          }
        },
        "bergmite": {
          "normal": {
            "isShiny": false,
            "status": "SEEN",
            "discoveredTimestamp": 1735147034771
          }
        },
        "eiscue": {
          "normal": {
            "isShiny": false,
            "status": "SEEN",
            "discoveredTimestamp": 1735147061343
          }
        },
        "seel": {
          "normal": {
            "isShiny": false,
            "status": "SEEN",
            "discoveredTimestamp": 1735147065026
          }
        },
        "gimmighoul": {
          "normal": {
            "isShiny": false,
            "status": "CAUGHT",
            "discoveredTimestamp": 1735147381362,
            "caughtTimestamp": 1735147381362
          },
          "roaming": {
            "isShiny": false,
            "status": "CAUGHT",
            "discoveredTimestamp": 1735229342345,
            "caughtTimestamp": 1735229358349
          }
        },
        "corvisquire": {
          "normal": {
            "isShiny": false,
            "status": "SEEN",
            "discoveredTimestamp": 1735147433820
          }
        },
        "spinarak": {
          "normal": {
            "isShiny": false,
            "status": "SEEN",
            "discoveredTimestamp": 1735147461270
          }
        },
        "forretress": {
          "normal": {
            "isShiny": false,
            "status": "SEEN",
            "discoveredTimestamp": 1735147575079
          }
        },
        "igglybuff": {
          "normal": {
            "isShiny": false,
            "status": "SEEN",
            "discoveredTimestamp": 1735147903768
          }
        },
        "swinub": {
          "normal": {
            "isShiny": false,
            "status": "CAUGHT",
            "discoveredTimestamp": 1735148278308,
            "caughtTimestamp": 1735149096414
          }
        },
        "goldeen": {
          "normal": {
            "isShiny": false,
            "status": "SEEN",
            "discoveredTimestamp": 1735148297256
          }
        },
        "basculin": {
          "bluestriped": {
            "isShiny": false,
            "status": "SEEN",
            "discoveredTimestamp": 1735148302908
          }
        },
        "squawkabilly": {
          "normal": {
            "isShiny": false,
            "status": "SEEN",
            "discoveredTimestamp": 1735148408131
          },
          "blue": {
            "isShiny": false,
            "status": "SEEN",
            "discoveredTimestamp": 1735148641120
          }
        },
        "electrode": {
          "hisui": {
            "isShiny": false,
            "status": "SEEN",
            "discoveredTimestamp": 1735148454964
          }
        },
        "rattata": {
          "normal": {
            "isShiny": false,
            "status": "SEEN",
            "discoveredTimestamp": 1735149032414
          }
        },
        "plusle": {
          "normal": {
            "isShiny": false,
            "status": "SEEN",
            "discoveredTimestamp": 1735149341518
          }
        },
        "umbreon": {
          "normal": {
            "isShiny": false,
            "status": "SEEN",
            "discoveredTimestamp": 1735149756429
          }
        },
        "wimpod": {
          "normal": {
            "isShiny": false,
            "status": "CAUGHT",
            "discoveredTimestamp": 1735149942553,
            "caughtTimestamp": 1735149942553
          }
        },
        "dachsbun": {
          "normal": {
            "isShiny": false,
            "status": "SEEN",
            "discoveredTimestamp": 1735150256985
          }
        },
        "bibarel": {
          "normal": {
            "isShiny": false,
            "status": "CAUGHT",
            "discoveredTimestamp": 1735150520132,
            "caughtTimestamp": 1735150599759
          }
        },
        "golbat": {
          "normal": {
            "isShiny": false,
            "status": "SEEN",
            "discoveredTimestamp": 1735219757931
          }
        },
        "yanma": {
          "normal": {
            "isShiny": false,
            "status": "SEEN",
            "discoveredTimestamp": 1735220358156
          }
        },
        "oddish": {
          "normal": {
            "isShiny": false,
            "status": "SEEN",
            "discoveredTimestamp": 1735221049457
          }
        },
        "marshtomp": {
          "normal": {
            "isShiny": false,
            "status": "CAUGHT",
            "discoveredTimestamp": 1735221219701,
            "caughtTimestamp": 1735221219701
          }
        },
        "spewpa": {
          "normal": {
            "isShiny": false,
            "status": "SEEN",
            "discoveredTimestamp": 1735221427992
          }
        },
        "pidgeot": {
          "normal": {
            "isShiny": false,
            "status": "CAUGHT",
            "discoveredTimestamp": 1735221681258,
            "caughtTimestamp": 1735227216951
          }
        },
        "gossifleur": {
          "normal": {
            "isShiny": false,
            "status": "SEEN",
            "discoveredTimestamp": 1735221829849
          }
        },
        "gloom": {
          "normal": {
            "isShiny": false,
            "status": "SEEN",
            "discoveredTimestamp": 1735222165159
          }
        },
        "jigglypuff": {
          "normal": {
            "isShiny": false,
            "status": "SEEN",
            "discoveredTimestamp": 1735222171063
          }
        },
        "mudsdale": {
          "normal": {
            "isShiny": false,
            "status": "SEEN",
            "discoveredTimestamp": 1735222206205
          }
        },
        "whimsicott": {
          "normal": {
            "isShiny": false,
            "status": "CAUGHT",
            "discoveredTimestamp": 1735222417411,
            "caughtTimestamp": 1735222417411
          }
        },
        "gumshoos": {
          "normal": {
            "isShiny": false,
            "status": "SEEN",
            "discoveredTimestamp": 1735222490756
          }
        },
        "buizel": {
          "normal": {
            "isShiny": false,
            "status": "SEEN",
            "discoveredTimestamp": 1735222708801
          }
        },
        "drifloon": {
          "normal": {
            "isShiny": false,
            "status": "CAUGHT",
            "discoveredTimestamp": 1735224276606,
            "caughtTimestamp": 1735224276606
          }
        },
        "archen": {
          "normal": {
            "isShiny": false,
            "status": "SEEN",
            "discoveredTimestamp": 1735224661199
          }
        },
        "weedle": {
          "normal": {
            "isShiny": false,
            "status": "SEEN",
            "discoveredTimestamp": 1735225519410
          }
        },
        "hoothoot": {
          "normal": {
            "isShiny": false,
            "status": "SEEN",
            "discoveredTimestamp": 1735226463220
          }
        },
        "surskit": {
          "normal": {
            "isShiny": false,
            "status": "SEEN",
            "discoveredTimestamp": 1735227349964
          }
        },
        "floatzel": {
          "normal": {
            "isShiny": false,
            "status": "SEEN",
            "discoveredTimestamp": 1735227541260
          }
        },
        "pichu": {
          "normal": {
            "isShiny": false,
            "status": "SEEN",
            "discoveredTimestamp": 1735228254612
          }
        },
        "prinplup": {
          "normal": {
            "isShiny": false,
            "status": "CAUGHT",
            "discoveredTimestamp": 1735228359899,
            "caughtTimestamp": 1735228359899
          }
        },
        "wooper": {
          "normal": {
            "isShiny": false,
            "status": "CAUGHT",
            "discoveredTimestamp": 1735230652355,
            "caughtTimestamp": 1735230652355
          }
        },
        "ditto": {
          "normal": {
            "isShiny": false,
            "status": "CAUGHT",
            "discoveredTimestamp": 1735230864471,
            "caughtTimestamp": 1735230864471
          }
        },
        "geodude": {
          "normal": {
            "isShiny": false,
            "status": "CAUGHT",
            "discoveredTimestamp": 1735232020696,
            "caughtTimestamp": 1735232020696
          }
        },
        "pelipper": {
          "normal": {
            "isShiny": false,
            "status": "SEEN",
            "discoveredTimestamp": 1735232559655
          }
        },
        "doduo": {
          "normal": {
            "isShiny": false,
            "status": "SEEN",
            "discoveredTimestamp": 1735232589162
          }
        },
        "phanpy": {
          "normal": {
            "isShiny": false,
            "status": "SEEN",
            "discoveredTimestamp": 1735232595956
          }
        },
        "spearow": {
          "normal": {
            "isShiny": false,
            "status": "SEEN",
            "discoveredTimestamp": 1735232601109
          }
        },
        "cufant": {
          "normal": {
            "isShiny": false,
            "status": "SEEN",
            "discoveredTimestamp": 1735232606306
          }
        },
        "ekans": {
          "normal": {
            "isShiny": false,
            "status": "CAUGHT",
            "discoveredTimestamp": 1735232660385,
            "caughtTimestamp": 1735232702408
          }
        },
        "arbok": {
          "normal": {
            "isShiny": false,
            "status": "CAUGHT",
            "discoveredTimestamp": 1735232714654,
            "caughtTimestamp": 1735232714654
          }
        },
        "ampharos": {
          "normal": {
            "isShiny": false,
            "status": "SEEN",
            "discoveredTimestamp": 1735232744303
          }
        },
        "kangaskhan": {
          "normal": {
            "isShiny": false,
            "status": "CAUGHT",
            "discoveredTimestamp": 1735232882001,
            "caughtTimestamp": 1735232882001
          }
        },
        "poochyena": {
          "normal": {
            "isShiny": false,
            "status": "CAUGHT",
            "discoveredTimestamp": 1735233034697,
            "caughtTimestamp": 1735233068559
          }
        },
        "woobat": {
          "normal": {
            "isShiny": false,
            "status": "SEEN",
            "discoveredTimestamp": 1735233083705
          }
        },
        "dodrio": {
          "normal": {
            "isShiny": false,
            "status": "SEEN",
            "discoveredTimestamp": 1735233095049
          }
        },
        "flittle": {
          "normal": {
            "isShiny": false,
            "status": "SEEN",
            "discoveredTimestamp": 1735233112750
          }
        },
        "nidoranm": {
          "normal": {
            "isShiny": false,
            "status": "SEEN",
            "discoveredTimestamp": 1735233252800
          }
        },
        "komala": {
          "normal": {
            "isShiny": false,
            "status": "SEEN",
            "discoveredTimestamp": 1735233342394
          }
        },
        "donphan": {
          "normal": {
            "isShiny": false,
            "status": "SEEN",
            "discoveredTimestamp": 1735233964521
          }
        },
        "shinx": {
          "normal": {
            "isShiny": false,
            "status": "CAUGHT",
            "discoveredTimestamp": 1735234275713,
            "caughtTimestamp": 1735234275713
          }
        },
        "luxio": {
          "normal": {
            "isShiny": false,
            "status": "CAUGHT",
            "discoveredTimestamp": 1735234287171,
            "caughtTimestamp": 1735234287171
          }
        },
        "nidoranf": {
          "normal": {
            "isShiny": false,
            "status": "SEEN",
            "discoveredTimestamp": 1735234561211
          }
        },
        "nidorina": {
          "normal": {
            "isShiny": false,
            "status": "SEEN",
            "discoveredTimestamp": 1735234567949
          }
        },
        "mightyena": {
          "normal": {
            "isShiny": false,
            "status": "CAUGHT",
            "discoveredTimestamp": 1735235147051,
            "caughtTimestamp": 1735235147051
          }
        },
        "farfetchd": {
          "normal": {
            "isShiny": false,
            "status": "SEEN",
            "discoveredTimestamp": 1735236132921
          }
        }
      },
      "name": "cobbledex_discovery"
    },
    "Cobbledex_RewardHistory": {
      "received": [
        "15",
        "30"
      ],
      "name": "Cobbledex_RewardHistory"
    }
  },
  "advancementData": {
    "totalCaptureCount": 35,
    "totalEggsHatched": 0,
    "totalEvolvedCount": 8,
    "totalBattleVictoryCount": 124,
    "totalPvPBattleVictoryCount": 0,
    "totalPvWBattleVictoryCount": 104,
    "totalPvNBattleVictoryCount": 20,
    "totalShinyCaptureCount": 0,
    "totalTradedCount": 2,
    "totalTypeCaptureCounts": {
      "fire": 1,
      "electric": 2,
      "normal": 10,
      "flying": 6,
      "steel": 2,
      "ghost": 4,
      "bug": 3,
      "ice": 2,
      "ground": 4,
      "water": 5,
      "psychic": 1,
      "grass": 2,
      "fairy": 2,
      "dark": 2,
      "rock": 1,
      "poison": 3
    },
    "totalDefeatedCounts": {
      "cobblemon:growlithe": 2,
      "cobblemon:weedle": 2,
      "cobblemon:shroomish": 1,
      "cobblemon:honedge": 1,
      "cobblemon:gimmighoul": 4,
      "cobblemon:tranquill": 1,
      "cobblemon:ponyta": 2,
      "cobblemon:zubat": 1,
      "cobblemon:swinub": 1,
      "cobblemon:timburr": 1,
      "cobblemon:slowpoke": 4,
      "cobblemon:dreepy": 1,
      "cobblemon:mareep": 1,
      "cobblemon:oddish": 2,
      "cobblemon:swellow": 1,
      "cobblemon:zigzagoon": 1,
      "cobblemon:bunnelby": 1,
      "cobblemon:igglybuff": 1,
      "cobblemon:minun": 1,
      "cobblemon:combee": 4,
      "cobblemon:taillow": 3,
      "cobblemon:tinkatink": 1,
      "cobblemon:furret": 1,
      "cobblemon:sentret": 1,
      "cobblemon:stonjourner": 1,
      "cobblemon:cutiefly": 1,
      "cobblemon:pidgey": 1,
      "cobblemon:deerling": 2,
      "cobblemon:linoone": 1,
      "cobblemon:bidoof": 1,
      "cobblemon:yanma": 1,
      "cobblemon:petilil": 2,
      "cobblemon:floette": 1,
      "cobblemon:floatzel": 1,
      "cobblemon:gastly": 1,
      "cobblemon:pichu": 1,
      "cobblemon:drifloon": 1,
      "cobblemon:buizel": 1,
      "cobblemon:rookidee": 1,
      "cobblemon:flittle": 1,
      "cobblemon:flabebe": 2,
      "cobblemon:woobat": 1,
      "cobblemon:patrat": 1,
      "cobblemon:wingull": 2,
      "cobblemon:krabby": 3,
      "cobblemon:pelipper": 2,
      "cobblemon:crabrawler": 3
    },
    "aspectsCollected": {}
  }
}